[{"hash":"aec0170b28e677e4bac80c729a18eefa","country":"AUSTRALIA","competition":"AUSTRALIA - A-LEAGUE P.OFF FINAL","home_team":"ΣΙΔΝΕΪ ΓΟΥΟΝΤΕΡΕΡΣ","away_team":"ΜΕΛΜΠΟΥΡΝ ΣΙΤΙ","home_rank":2.2,"draw_rank":3.3,"away_rank":2.55,"first_half":"1 - 1","result_score":"3 - 1","result":"1","home_team_goals":3,"away_team_goals":1,"total_goals":4},{"hash":"5aa5f5078080517c4c930a1027e5c8ac","country":"AUSTRALIA","competition":"AUSTRALIA - NSW P.OFF SF","home_team":"ΧΟΜΠΑΡΤ ΖΕΜΠΡΑΣ","away_team":"ΝΟΤΙΑ ΧΟΜΠΑΡΤ","home_rank":2.4,"draw_rank":3.6,"away_rank":2.2,"first_half":"1 - 0","result_score":"3 - 0","result":"1","home_team_goals":3,"away_team_goals":0,"total_goals":3},{"hash":"8649987c8b634fe58d5ff191760129d3","country":"AUSTRALIA","competition":"AUSTRALIA - NSW P.OFF SF","home_team":"ΠΑΣΚΟΕ ΒΑΛΕ","away_team":"ΚΙΝΓΚΣΤΟΝ ΣΙΤΙ","home_rank":2.05,"draw_rank":3.35,"away_rank":2.75,"first_half":"2 - 0","result_score":"2 - 0","result":"1","home_team_goals":2,"away_team_goals":0,"total_goals":2},{"hash":"c7abfb7d4977ef399f5171f5f2976640","country":"AUSTRALIA","competition":"AUSTRALIA - NSW P.OFF SF","home_team":"ΜΠΕΝΤΛΙ ΓΚΡΙΝΣ","away_team":"ΑΛΜΠΑΝΣ ΣΕΪΝΤΣ","home_rank":1.2,"draw_rank":5.4,"away_rank":7.75,"first_half":"2 - 0","result_score":"3 - 0","result":"1","home_team_goals":3,"away_team_goals":0,"total_goals":3},{"hash":"9dc5d9fedbc8843c139a7ea7fac159d2","country":"AUSTRALIA","competition":"AUSTRALIA - NSW P.OFF SF","home_team":"ΟΚΛΙ ΚΑΝΟΝΣ","away_team":"ΝΟΤΙΑ ΜΕΛΒΟΥΡΝΗ","home_rank":2.6,"draw_rank":3.25,"away_rank":2.18,"first_half":"0 - 0","result_score":"1 - 0","result":"1","home_team_goals":1,"away_team_goals":0,"total_goals":1},{"hash":"b063ad1eedc7b072ec5db818edcb7135","country":"AUSTRALIA","competition":"AUSTRALIA - NSW P.OFF SF","home_team":"ΜΕΛΒΟΥΡΝΗ ΝΑΪΤΣ","away_team":"ΠΟΡΤ ΜΕΛΒΟΥΡΝΗ Σ.","home_rank":1.92,"draw_rank":3.4,"away_rank":3,"first_half":"3 - 0","result_score":"4 - 0","result":"1","home_team_goals":4,"away_team_goals":0,"total_goals":4},{"hash":"b1d11751bb16cf97463cae698246aef7","country":"EUROPE (UEFA)","competition":"EUROPE (UEFA) - FINAL","home_team":"ΑΥΣΤΡΙΑ U19","away_team":"ΟΥΓΓΑΡΙΑ U19","home_rank":1.57,"draw_rank":3.6,"away_rank":4.25,"first_half":"1 - 2","result_score":"1 - 3","result":"2","home_team_goals":1,"away_team_goals":3,"total_goals":4},{"hash":"6878089b14c0dfa5ab04fa60327608a3","country":"AUSTRALIA","competition":"AUSTRALIA - NSW P.OFF SF","home_team":"ΜΠΡΙΣΜΠΕΪΝ ΣΙΤΙ","away_team":"ΓΟΥΕΣΤΕΡΝ ΠΡΑΪΝΤ","home_rank":1.38,"draw_rank":4.3,"away_rank":5.2,"first_half":"2 - 0","result_score":"2 - 2","result":"X","home_team_goals":2,"away_team_goals":2,"total_goals":4},{"hash":"286cb6abc4a13a48b28cf58a3ff7f25d","country":"EUROPE (UEFA)","competition":"EUROPE (UEFA) - QUALIFYING ROUND","home_team":"ΠΓΔΜ U21","away_team":"ΜΑΥΡΟΒΟΥΝΙΟ U21","home_rank":1.85,"draw_rank":3.1,"away_rank":3.45,"first_half":"1 - 0","result_score":"2 - 0","result":"1","home_team_goals":2,"away_team_goals":0,"total_goals":2},{"hash":"6682f5516a435975493819cdbaec2375","country":"EUROPE (UEFA)","competition":"EUROPE (UEFA) - FINAL","home_team":"ΙΣΠΑΝΙΑ U19","away_team":"ΑΓΓΛΙΑ U19","home_rank":2.25,"draw_rank":3.05,"away_rank":2.65,"first_half":"0 - 1","result_score":"0 - 3","result":"2","home_team_goals":0,"away_team_goals":3,"total_goals":3},{"hash":"3042e575ce031ddea334420cb05d32c3","country":"EUROPE (UEFA)","competition":"EUROPE (UEFA) - FINAL","home_team":"ΝΟΡΒΗΓΙΑ U19","away_team":"ΛΕΥΚΟΡΩΣΙΑ  U19","home_rank":1.42,"draw_rank":3.65,"away_rank":5.7,"first_half":"2 - 0","result_score":"2 - 1","result":"1","home_team_goals":2,"away_team_goals":1,"total_goals":3},{"hash":"8cea06d797015ddf640bd047defb5846","country":"FRIENDLY GAMES","competition":"FRIENDLY GAMES - FRIENDLY","home_team":"ΜΠΡΑΟΥΝΣΒΑΪΓΚ","away_team":"ΜΠΕΡΛΙΝΕΡ","home_rank":1.33,"draw_rank":4.2,"away_rank":6.25,"first_half":"5 - 0","result_score":"6 - 0","result":"1","home_team_goals":6,"away_team_goals":0,"total_goals":6},{"hash":"07e2aab73d40d5cdf501ee262c2e12af","country":"FRIENDLY GAMES","competition":"FRIENDLY GAMES - FRIENDLY","home_team":"ΧΑΜΑΡΜΠΙ","away_team":"ΙΛΒΕΣ","home_rank":1.33,"draw_rank":4.2,"away_rank":6.25,"first_half":"1 - 0","result_score":"4 - 0","result":"1","home_team_goals":4,"away_team_goals":0,"total_goals":4},{"hash":"e77ffda2734e703d5db2e84e81267120","country":"FRIENDLY GAMES","competition":"FRIENDLY GAMES - FRIENDLY","home_team":"ΜΑΤΕΡΣΜΠΟΥΡΓΚ","away_team":"ΛΙΝΤΖ","home_rank":1.58,"draw_rank":3.75,"away_rank":4,"first_half":"1 - 0","result_score":"4 - 0","result":"1","home_team_goals":4,"away_team_goals":0,"total_goals":4},{"hash":"bfbce1e1b571a07532a7c1476d88e85f","country":"FRIENDLY GAMES","competition":"FRIENDLY GAMES - FRIENDLY","home_team":"ΡΙΝΤ","away_team":"ΝΤΟΥΚΛΑ ΠΡΑΓΑΣ","home_rank":2.5,"draw_rank":3.1,"away_rank":2.3,"first_half":"1 - 0","result_score":"2 - 1","result":"1","home_team_goals":2,"away_team_goals":1,"total_goals":3},{"hash":"f2325e65eeb51be5fe36cccb91d7bd6e","country":"EUROPE (UEFA)","competition":"EUROPE (UEFA) - QUALIFYING ROUND","home_team":"ΤΟΥΡΚΙΑ U21","away_team":"ΟΥΚΡΑΝΙΑ U21","home_rank":2.25,"draw_rank":2.95,"away_rank":2.7,"first_half":"1 - 0","result_score":"1 - 1","result":"X","home_team_goals":1,"away_team_goals":1,"total_goals":2},{"hash":"23be0446b3482587eb27376cb3a1f77d","country":"FRIENDLY GAMES","competition":"FRIENDLY GAMES - FRIENDLY","home_team":"ΕΛΣΙΝΚΙ","away_team":"ΤΑΛΙΝ ΙΝΦΟΝΕΤ","home_rank":1.33,"draw_rank":4.3,"away_rank":5.9,"first_half":"2 - 0","result_score":"3 - 0","result":"1","home_team_goals":3,"away_team_goals":0,"total_goals":3},{"hash":"508871f946b23446007f1ee12d102948","country":"ALGERIA","competition":"ALGERIA - LIGUE 1","home_team":"ΤΑΝΤΕΝΑΝΤ","away_team":"ΜΠΕΖΑΓΙΑ","home_rank":1.47,"draw_rank":3.25,"away_rank":6.25,"first_half":"1 - 1","result_score":"1 - 1","result":"X","home_team_goals":1,"away_team_goals":1,"total_goals":2},{"hash":"3d74f6eb8dc419850a1a072f88a71efe","country":"FRIENDLY GAMES","competition":"FRIENDLY GAMES - FRIENDLY","home_team":"ΜΟΝΑΧΟ 1860","away_team":"ΒΑΚΕΡ ΙΝΣΜΠΟΥΡΓΚ","home_rank":1.48,"draw_rank":3.9,"away_rank":4.6,"first_half":"2 - 0","result_score":"2 - 0","result":"1","home_team_goals":2,"away_team_goals":0,"total_goals":2},{"hash":"18b2ae137b26c6fd86f20fcacb7118de","country":"FRIENDLY GAMES","competition":"FRIENDLY GAMES - FRIENDLY","home_team":"ΓΚΛΑΝΤΜΠΑΧ","away_team":"ΣΑΙΝΤ ΠΑΟΥΛΙ","home_rank":1.65,"draw_rank":3.6,"away_rank":3.7,"first_half":"1 - 1","result_score":"4 - 4","result":"X","home_team_goals":4,"away_team_goals":4,"total_goals":8},{"hash":"76916bdc0894a4dfc952acd47d048196","country":"EUROPE (UEFA)","competition":"EUROPE (UEFA) - QUALIFYING ROUND","home_team":"ΡΩΣΙΑ U21","away_team":"ΡΟΥΜΑΝΙΑ U21","home_rank":1.72,"draw_rank":3.25,"away_rank":3.75,"first_half":"1 - 0","result_score":"5 - 1","result":"1","home_team_goals":5,"away_team_goals":1,"total_goals":6},{"hash":"607e2befc8c7f0b616899499e81f3834","country":"EUROPE (UEFA)","competition":"EUROPE (UEFA) - QUALIFYING ROUND","home_team":"ΟΛΛΑΝΔΙΑ U21","away_team":"ΦΙΝΛΑΝΔΙΑ U21","home_rank":1.2,"draw_rank":4.7,"away_rank":9.5,"first_half":"0 - 0","result_score":"2 - 0","result":"1","home_team_goals":2,"away_team_goals":0,"total_goals":2},{"hash":"44e1be7100b428057e1f1d61903af29f","country":"EUROPE (UEFA)","competition":"EUROPE (UEFA) - FINAL","home_team":"ΙΣΡΑΗΛ U19","away_team":"ΒΟΣΝΙΑ-ΕΡΖΕΓΟΒΙΝΗ U19","home_rank":2.25,"draw_rank":3,"away_rank":2.65,"first_half":"1 - 1","result_score":"1 - 1","result":"X","home_team_goals":1,"away_team_goals":1,"total_goals":2},{"hash":"01f0eb5d5f74c1218cef65f9df0f454d","country":"EGYPT","competition":"EGYPT - DIVISION 1","home_team":"ΜΙΣΤ ΛΕΛ ΜΑΚΑΣΑ","away_team":"ΑΛ-ΜΑΣΡΙ","home_rank":2.25,"draw_rank":2.6,"away_rank":3.05,"first_half":"","result_score":"","result":"","home_team_goals":null,"away_team_goals":null,"total_goals":null},{"hash":"5dc688a0f07512ccf4ef51ea4fcfae87","country":"EUROPE (UEFA)","competition":"EUROPE (UEFA) - QUALIFYING ROUND","home_team":"ΤΣΕΧΙΑ U21","away_team":"ΣΛΟΒΑΚΙΑ U21","home_rank":2.25,"draw_rank":3.05,"away_rank":2.6,"first_half":"4 - 0","result_score":"4 - 1","result":"1","home_team_goals":4,"away_team_goals":1,"total_goals":5},{"hash":"d84417cda927ec0f8a73a37b7b164aa0","country":"EUROPE (UEFA)","competition":"EUROPE (UEFA) - FINAL","home_team":"ΤΣΕΧΙΑ U19","away_team":"ΣΚΩΤΙΑ U19","home_rank":1.72,"draw_rank":3.2,"away_rank":3.85,"first_half":"0 - 0","result_score":"1 - 0","result":"1","home_team_goals":1,"away_team_goals":0,"total_goals":1},{"hash":"f358e0edfb4860b340d7cf5fd8b2dc81","country":"FRIENDLY GAMES","competition":"FRIENDLY GAMES - FRIENDLY","home_team":"ΡΩΣΙΑ","away_team":"ΑΚΤΗ ΕΛΕΦΑΝΤΟΣΤΟΥ","home_rank":1.68,"draw_rank":3.05,"away_rank":4.4,"first_half":"0 - 1","result_score":"0 - 2","result":"2","home_team_goals":0,"away_team_goals":2,"total_goals":2},{"hash":"a44bb8aaae8df86c87fadcff645be649","country":"POLAND","competition":"POLAND - I LIGA","home_team":"ΠΟΝΜΠΕΣΚΙΤΖΙΕ","away_team":"ΣΤΟΜΙΛ","home_rank":1.92,"draw_rank":3.05,"away_rank":3.3,"first_half":"1 - 0","result_score":"2 - 2","result":"X","home_team_goals":2,"away_team_goals":2,"total_goals":4},{"hash":"b725785f884128f859db02435e513bbd","country":"WORLD (FIFA)","competition":"WORLD (FIFA) - INTER CONFED. P.OFFS (CONCACAF v AFC)","home_team":"ΓΕΩΡΓΙΑ","away_team":"ΣΕΡΒΙΑ","home_rank":5.5,"draw_rank":3.5,"away_rank":1.5,"first_half":"1 - 1","result_score":"1 - 3","result":"2","home_team_goals":1,"away_team_goals":3,"total_goals":4},{"hash":"c2ad7f7be58de47ad985ce72a41fdadc","country":"WORLD (FIFA)","competition":"WORLD (FIFA) - INTER CONFED. P.OFFS (CONCACAF v AFC)","home_team":"ΤΟΥΡΚΙΑ","away_team":"ΦΙΝΛΑΝΔΙΑ","home_rank":1.3,"draw_rank":4,"away_rank":8.75,"first_half":"2 - 0","result_score":"2 - 0","result":"1","home_team_goals":2,"away_team_goals":0,"total_goals":2},{"hash":"f76fe2f6a6a1a0caeae8f2e470dabf7c","country":"FRIENDLY GAMES","competition":"FRIENDLY GAMES - FRIENDLY","home_team":"ΑΟΥΕ","away_team":"ΝΤΙΝΑΜΟ ΜΠΡΕΣΤ","home_rank":1.77,"draw_rank":3.6,"away_rank":3.25,"first_half":"0 - 0","result_score":"0 - 0","result":"X","home_team_goals":0,"away_team_goals":0,"total_goals":0},{"hash":"15957e22544bd95300dbf064f05002b1","country":"FRIENDLY GAMES","competition":"FRIENDLY GAMES - FRIENDLY","home_team":"ΑΪΝΤΡΑΧΤ ΦΡ.","away_team":"ΚΙΚΕΡΣ ΒΟΥΡΖ.","home_rank":1.78,"draw_rank":3.35,"away_rank":3.4,"first_half":"0 - 0","result_score":"0 - 1","result":"2","home_team_goals":0,"away_team_goals":1,"total_goals":1},{"hash":"ea01f8cf22c9a2b1fe8d3032c85a53ee","country":"FRIENDLY GAMES","competition":"FRIENDLY GAMES - FRIENDLY","home_team":"ΡΟΖΕΛΑΡ","away_team":"ΒΑΑΣΛΑΝΤ ΜΠΕΒΕΡΕΝ","home_rank":2.25,"draw_rank":3.2,"away_rank":2.5,"first_half":"0 - 1","result_score":"0 - 2","result":"2","home_team_goals":0,"away_team_goals":2,"total_goals":2},{"hash":"c10b1f42670b4716389e195b716d9937","country":"WORLD (FIFA)","competition":"WORLD (FIFA) - FINAL","home_team":"ΤΣΕΧΙΑ U20","away_team":"ΔΑΝΙΑ U20","home_rank":2.5,"draw_rank":3.1,"away_rank":2.3,"first_half":"0 - 0","result_score":"1 - 2","result":"2","home_team_goals":1,"away_team_goals":2,"total_goals":3},{"hash":"ccb53cc2f083ea5eb450c36db1822387","country":"GERMANY","competition":"GERMANY - REGIONAL LEAGUE NORTH","home_team":"ΙΛΕΡΤΙΣΕΝ","away_team":"ΜΠΟΥΡΓΚΧΑΟΥΖΕΝ","home_rank":2.5,"draw_rank":3,"away_rank":2.35,"first_half":"0 - 0","result_score":"1 - 0","result":"1","home_team_goals":1,"away_team_goals":0,"total_goals":1},{"hash":"103885626125a987b2a8045c36e6d521","country":"EUROPE (UEFA)","competition":"EUROPE (UEFA) - FINAL","home_team":"ΓΑΛΛΙΑ U19","away_team":"ΒΟΥΛΓΑΡΙΑ U19","home_rank":1.07,"draw_rank":6.5,"away_rank":16.5,"first_half":"0 - 1","result_score":"1 - 2","result":"2","home_team_goals":1,"away_team_goals":2,"total_goals":3},{"hash":"74f11a4aae953b44558adc76f1b6d97f","country":"FRIENDLY GAMES","competition":"FRIENDLY GAMES - FRIENDLY","home_team":"ΤΥΝΗΣΙΑ","away_team":"ΚΑΜΕΡΟΥΝ","home_rank":2.25,"draw_rank":2.75,"away_rank":2.95,"first_half":"0 - 1","result_score":"0 - 1","result":"2","home_team_goals":0,"away_team_goals":1,"total_goals":1},{"hash":"3e8be7b76983ee981a292e7c511deca6","country":"GERMANY","competition":"GERMANY - REGIONAL LEAGUE NORTH","home_team":"ΣΒΑΪΝΦΟΥΡΤ","away_team":"ΟΥΝΤΕΡΧΑΚΙΝΓΚ","home_rank":4.2,"draw_rank":3.5,"away_rank":1.58,"first_half":"1 - 0","result_score":"2 - 1","result":"1","home_team_goals":2,"away_team_goals":1,"total_goals":3},{"hash":"cb8983b4c576afc4c6ba68deeff424c8","country":"GERMANY","competition":"GERMANY - REGIONAL LEAGUE NORTH","home_team":"ΒΕΡΛ","away_team":"ΕΣΕΝ","home_rank":2.8,"draw_rank":2.95,"away_rank":2.2,"first_half":"0 - 0","result_score":"0 - 0","result":"X","home_team_goals":0,"away_team_goals":0,"total_goals":0},{"hash":"a89af1bbfdae30ee5f64453eaea64e08","country":"GERMANY","competition":"GERMANY - REGIONAL LEAGUE NORTH","home_team":"ΧΕΣΣΕΝ ΚΑΣΣΕΛ","away_team":"ΣΤΙΝΜΠΑΧ","home_rank":3.4,"draw_rank":3,"away_rank":1.92,"first_half":"0 - 0","result_score":"0 - 0","result":"X","home_team_goals":0,"away_team_goals":0,"total_goals":0},{"hash":"ca210cde19bca9f24abcae36d52ed610","country":"EUROPE (UEFA)","competition":"EUROPE (UEFA) - QUALIFYING ROUND","home_team":"ΠΟΡΤΟΓΑΛΙΑ U21","away_team":"ΝΟΡΒΗΓΙΑ U21","home_rank":1.16,"draw_rank":4.9,"away_rank":11.5,"first_half":"1 - 0","result_score":"3 - 1","result":"1","home_team_goals":3,"away_team_goals":1,"total_goals":4},{"hash":"be83fd5a55558f0a4a26101960cc88b1","country":"ARGENTINA","competition":"ARGENTINA - PRIMERA B NACIONAL","home_team":"ΛΟΣ ΑΝΤΕΣ","away_team":"ΝΤΑΓΚΛΑΣ ΧΕΓΚ","home_rank":1.93,"draw_rank":2.8,"away_rank":3.6,"first_half":"1 - 0","result_score":"1 - 0","result":"1","home_team_goals":1,"away_team_goals":0,"total_goals":1},{"hash":"f05695cd959af4c7f54daff5f3bdfb73","country":"EUROPE (UEFA)","competition":"EUROPE (UEFA) - QUALIFYING ROUND","home_team":"ΓΕΡΜΑΝΙΑ U21","away_team":"ΑΓΓΛΙΑ U21","home_rank":1.75,"draw_rank":3.35,"away_rank":3.5,"first_half":"1 - 0","result_score":"1 - 0","result":"1","home_team_goals":1,"away_team_goals":0,"total_goals":1},{"hash":"cae48f8094956d8d773e9760d02732c1","country":"FRANCE","competition":"FRANCE - CHAMPIONNAT NATIONAL","home_team":"ΑΒΡΑΝΣ","away_team":"ΛΥΩΝ ΝΤΟΥΤΣΕΡΕ","home_rank":2.1,"draw_rank":2.85,"away_rank":3.1,"first_half":"0 - 1","result_score":"0 - 2","result":"2","home_team_goals":0,"away_team_goals":2,"total_goals":2},{"hash":"851dd0b8b689829a35182dd181bff361","country":"FRANCE","competition":"FRANCE - CHAMPIONNAT NATIONAL","home_team":"ΚΟΝΣΟΛΑΤ","away_team":"ΣΑΤΟΡΟΥ","home_rank":3,"draw_rank":2.85,"away_rank":2.15,"first_half":"1 - 2","result_score":"1 - 3","result":"2","home_team_goals":1,"away_team_goals":3,"total_goals":4},{"hash":"9fecb52b4aa6e97e73e67b2ab9a6d27b","country":"FRANCE","competition":"FRANCE - CHAMPIONNAT NATIONAL","home_team":"ΚΡΕΤΕΪΓ","away_team":"ΛΕΣ ΧΕΡΜΠΙΕΡΣ","home_rank":2.15,"draw_rank":2.8,"away_rank":3.05,"first_half":"1 - 2","result_score":"2 - 3","result":"2","home_team_goals":2,"away_team_goals":3,"total_goals":5},{"hash":"d2359402ce0ca51608e2d5bda8cdb906","country":"FRANCE","competition":"FRANCE - CHAMPIONNAT NATIONAL","home_team":"ΜΠΕΖΙΕΡ","away_team":"ΣΑΜΠΛΙ ΤΧΕΛΕ","home_rank":2.3,"draw_rank":2.65,"away_rank":2.9,"first_half":"2 - 1","result_score":"5 - 2","result":"1","home_team_goals":5,"away_team_goals":2,"total_goals":7},{"hash":"01ceaf9496b2a56302b858cf06fe205d","country":"FRANCE","competition":"FRANCE - CHAMPIONNAT NATIONAL","home_team":"ΜΠΕΛΦΟΡΤ","away_team":"ΜΠΟΥΛΟΝ","home_rank":3.1,"draw_rank":2.8,"away_rank":2.12,"first_half":"0 - 1","result_score":"0 - 2","result":"2","home_team_goals":0,"away_team_goals":2,"total_goals":2},{"hash":"8ba0dfb7e57fc52c406c78e3520262eb","country":"FRANCE","competition":"FRANCE - CHAMPIONNAT NATIONAL","home_team":"ΠΑΡΙ","away_team":"ΕΠΙΝΑΛ","home_rank":1.7,"draw_rank":2.9,"away_rank":4.6,"first_half":"0 - 0","result_score":"1 - 0","result":"1","home_team_goals":1,"away_team_goals":0,"total_goals":1},{"hash":"1e515f2bc071a7ba1c63eb2fe523701f","country":"FRANCE","competition":"FRANCE - CHAMPIONNAT NATIONAL","home_team":"ΣΕΝΤΑΝ","away_team":"ΠΟ","home_rank":2.02,"draw_rank":2.75,"away_rank":3.45,"first_half":"2 - 0","result_score":"2 - 0","result":"1","home_team_goals":2,"away_team_goals":0,"total_goals":2},{"hash":"91a363211f6c8a624a9c4fc0feae7324","country":"FRANCE","competition":"FRANCE - CHAMPIONNAT NATIONAL","home_team":"ΣΕΡΚΛ ΜΠΑΣΤΙΑ","away_team":"ΚΙΟΥΒΕΓΙ","home_rank":2.6,"draw_rank":2.85,"away_rank":2.4,"first_half":"0 - 0","result_score":"1 - 1","result":"X","home_team_goals":1,"away_team_goals":1,"total_goals":2},{"hash":"fd40f40124bf1055dafbc2231068ea7a","country":"BELGIUM","competition":"BELGIUM - EUROPA LEAGUE P.OFF FINAL","home_team":"ΛΕΟΥΒΕΝ","away_team":"ΤΟΥΜΠΙΖΕ","home_rank":2.15,"draw_rank":3.1,"away_rank":2.75,"first_half":"0 - 1","result_score":"1 - 1","result":"X","home_team_goals":1,"away_team_goals":1,"total_goals":2},{"hash":"41ebf12c6d107e9e6ae03da970f4ad08","country":"EUROPE (UEFA)","competition":"EUROPE (UEFA) - QUALIFYING ROUND","home_team":"ΣΕΡΒΙΑ U21","away_team":"ΣΟΥΗΔΙΑ U21","home_rank":2.7,"draw_rank":3.05,"away_rank":2.2,"first_half":"2 - 0","result_score":"2 - 0","result":"1","home_team_goals":2,"away_team_goals":0,"total_goals":2},{"hash":"6e851bdbc03d78c9deb782174673ba74","country":"ENGLAND","competition":"ENGLAND - SOUTHERN FOOTBALL LEAGUE","home_team":"ΧΕΪΣ & ΓΙΝΤΙΝΓΚ","away_team":"ΣΕΝ ΝΕΟΤΣ ΤΑΟΥΝ","home_rank":2.15,"draw_rank":3.4,"away_rank":2.55,"first_half":"2 - 0","result_score":"2 - 0","result":"1","home_team_goals":2,"away_team_goals":0,"total_goals":2},{"hash":"7e147f363ed5192ed87ae319c9aa51ae","country":"NORTHERN IRELAND","competition":"NORTHERN IRELAND - NIFL PREMIERSHIP","home_team":"ΓΚΛΕΝΤΟΡΑΝ","away_team":"ΚΑΡΙΚ ΡΕΪΝΤΖΕΡΣ","home_rank":1.45,"draw_rank":3.8,"away_rank":4.9,"first_half":"0 - 0","result_score":"1 - 0","result":"1","home_team_goals":1,"away_team_goals":0,"total_goals":1},{"hash":"e7079bd8d0955d45448bbba019059750","country":"WORLD (FIFA)","competition":"WORLD (FIFA) - INTER CONFED. P.OFFS (CONCACAF v AFC)","home_team":"ΑΥΣΤΡΙΑ","away_team":"ΜΟΛΔΑΒΙΑ","home_rank":1.06,"draw_rank":7.25,"away_rank":19,"first_half":"0 - 0","result_score":"2 - 0","result":"1","home_team_goals":2,"away_team_goals":0,"total_goals":2},{"hash":"36ec11b8dfe5089128edb9b0cefbc09f","country":"WORLD (FIFA)","competition":"WORLD (FIFA) - INTER CONFED. P.OFFS (CONCACAF v AFC)","home_team":"ΙΡΛΑΝΔΙΑ","away_team":"ΟΥΑΛΙΑ","home_rank":2.3,"draw_rank":2.8,"away_rank":2.95,"first_half":"0 - 0","result_score":"0 - 0","result":"X","home_team_goals":0,"away_team_goals":0,"total_goals":0},{"hash":"c94b3844407f1a378a2312c4a5672b30","country":"WORLD (FIFA)","competition":"WORLD (FIFA) - INTER CONFED. P.OFFS (CONCACAF v AFC)","home_team":"ΙΣΠΑΝΙΑ","away_team":"ΙΣΡΑΗΛ","home_rank":1.02,"draw_rank":9,"away_rank":23,"first_half":"2 - 0","result_score":"4 - 1","result":"1","home_team_goals":4,"away_team_goals":1,"total_goals":5},{"hash":"da4e990fed243f00775108ea3fae262b","country":"WORLD (FIFA)","competition":"WORLD (FIFA) - INTER CONFED. P.OFFS (CONCACAF v AFC)","home_team":"ΙΤΑΛΙΑ","away_team":"ΑΛΒΑΝΙΑ","home_rank":1.1,"draw_rank":6,"away_rank":17,"first_half":"1 - 0","result_score":"2 - 0","result":"1","home_team_goals":2,"away_team_goals":0,"total_goals":2},{"hash":"90e5046d1e535a8bcd011600f6de466e","country":"WORLD (FIFA)","competition":"WORLD (FIFA) - INTER CONFED. P.OFFS (CONCACAF v AFC)","home_team":"ΚΟΣΟΒΟ","away_team":"ΙΣΛΑΝΔΙΑ","home_rank":11,"draw_rank":5.3,"away_rank":1.17,"first_half":"0 - 2","result_score":"1 - 2","result":"2","home_team_goals":1,"away_team_goals":2,"total_goals":3},{"hash":"15ee32c621a779b9f9bd73908235797b","country":"WORLD (FIFA)","competition":"WORLD (FIFA) - INTER CONFED. P.OFFS (CONCACAF v AFC)","home_team":"ΚΡΟΑΤΙΑ","away_team":"ΟΥΚΡΑΝΙΑ","home_rank":1.4,"draw_rank":3.75,"away_rank":6.5,"first_half":"1 - 0","result_score":"1 - 0","result":"1","home_team_goals":1,"away_team_goals":0,"total_goals":1},{"hash":"c4b43a4570ddd74071a886f2739bdb64","country":"WORLD (FIFA)","competition":"WORLD (FIFA) - INTER CONFED. P.OFFS (CONCACAF v AFC)","home_team":"ΛΙΧΤΕΝΣΤΑΪΝ","away_team":"ΠΓΔΜ","home_rank":6.75,"draw_rank":3.9,"away_rank":1.37,"first_half":"0 - 1","result_score":"0 - 3","result":"2","home_team_goals":0,"away_team_goals":3,"total_goals":3},{"hash":"bfe2f2b53aa3132715624188274d5cc0","country":"FRIENDLY GAMES","competition":"FRIENDLY GAMES - FRIENDLY","home_team":"ΜΑΡΟΚΟ","away_team":"ΜΠΟΥΡΚΙΝΑ ΦΑΣΟ","home_rank":1.58,"draw_rank":3.05,"away_rank":5.2,"first_half":"1 - 0","result_score":"2 - 0","result":"1","home_team_goals":2,"away_team_goals":0,"total_goals":2},{"hash":"8cc1486727aaf4110f192ee9d8bf4899","country":"PARAGUAY","competition":"PARAGUAY - CLAUSURA","home_team":"ΣΟΛ ΝΤΕ ΑΜΕΡΙΚΑ","away_team":"ΣΠΟΡΤΙΒΟ ΤΡΙΝΙΝΤΕΝΣΕ","home_rank":1.57,"draw_rank":3.6,"away_rank":4.3,"first_half":"0 - 0","result_score":"3 - 0","result":"1","home_team_goals":3,"away_team_goals":0,"total_goals":3},{"hash":"582f8baebd6473ce5a41dadbfe157335","country":"VENEZUELA","competition":"VENEZUELA - CLAUSURA","home_team":"ΝΤΕΠΟΡΤΙΒΟ ΤΑΤΣΙΡΑ","away_team":"ΠΟΡΤΟΥΓΚΕΖΑ","home_rank":1.45,"draw_rank":3.85,"away_rank":4.9,"first_half":"0 - 0","result_score":"1 - 1","result":"X","home_team_goals":1,"away_team_goals":1,"total_goals":2},{"hash":"28b9d04f15e47351262d064800978881","country":"WORLD (FIFA)","competition":"WORLD (FIFA) - INTER CONFED. P.OFFS (CONCACAF v AFC)","home_team":"ΤΡΙΝΙΝΤΑΝΤ & ΤΟΜΠΑΓΚΟ","away_team":"ΠΑΝΑΜΑΣ","home_rank":3.25,"draw_rank":2.75,"away_rank":2.1,"first_half":"1 - 0","result_score":"1 - 0","result":"1","home_team_goals":1,"away_team_goals":0,"total_goals":1},{"hash":"356c58a0781997c112ccb6f6a3567025","country":"ARGENTINA","competition":"ARGENTINA - PRIMERA B NACIONAL","home_team":"ΑΡΧΕΝΤΙΝΟΣ ΤΖΟΥΝ.","away_team":"ΣΑΝ ΜΑΡΤΙΝ ΤΟΥΚΟΥΜΑΝ","home_rank":1.55,"draw_rank":3.1,"away_rank":5.4,"first_half":"1 - 0","result_score":"3 - 1","result":"1","home_team_goals":3,"away_team_goals":1,"total_goals":4},{"hash":"c1aa746f3b6646c531521917fac92633","country":"PARAGUAY","competition":"PARAGUAY - CLAUSURA","home_team":"ΡΟΥΜΠΙΟ ΝΟΥ","away_team":"ΣΠΟΡΤΙΒΟ ΛΟΥΚΕΝΙΟ","home_rank":2.65,"draw_rank":2.95,"away_rank":2.3,"first_half":"0 - 0","result_score":"1 - 1","result":"X","home_team_goals":1,"away_team_goals":1,"total_goals":2},{"hash":"2f30cfcc09999dfc0520c9809a32f482","country":"ARGENTINA","competition":"ARGENTINA - SUPERLIGA ARGENTINA","home_team":"ΠΑΤΡΟΝΑΤΟ ΠΑΡΑΝΑ","away_team":"ΝΙΟΥΕΛΣ ΟΛΝΤ ΜΠΟΪΣ","home_rank":2.7,"draw_rank":2.75,"away_rank":2.4,"first_half":"1 - 0","result_score":"1 - 1","result":"X","home_team_goals":1,"away_team_goals":1,"total_goals":2},{"hash":"e61ce60ded9e699294a75df4e852392f","country":"ARGENTINA","competition":"ARGENTINA - PRIMERA B NACIONAL","home_team":"ΙΝΤΕΠ. ΡΙΒΑΝΤΑΒΙΑ","away_team":"ΓΚΙΓΙΕΡΜΟ ΜΠΡΑΟΥΝ","home_rank":2.2,"draw_rank":2.8,"away_rank":2.9,"first_half":"0 - 1","result_score":"1 - 1","result":"X","home_team_goals":1,"away_team_goals":1,"total_goals":2},{"hash":"d8696d40ed1e6792e3f31b2a8617c5cd","country":"MEXICO","competition":"MEXICO - CL2-P.OFF FINAL","home_team":"ΑΤΛΑΝΤΕ","away_team":"ΚΟΡΑΣ","home_rank":2.1,"draw_rank":3.15,"away_rank":2.8,"first_half":"0 - 0","result_score":"0 - 2","result":"2","home_team_goals":0,"away_team_goals":2,"total_goals":2},{"hash":"48608a8f60984eb48f46e316bf9f8b78","country":"ECUADOR","competition":"ECUADOR - DIVISION 1 STAGE 2","home_team":"ΝΤΕΠΟΡΤΙΒΟ ΚΟΥΕΝΚΑ","away_team":"ΝΤΕΛΦΙΝ","home_rank":1.68,"draw_rank":3.15,"away_rank":4.2,"first_half":"0 - 0","result_score":"1 - 1","result":"X","home_team_goals":1,"away_team_goals":1,"total_goals":2},{"hash":"0a9502abd9233006f439f28d0265a10c","country":"WORLD (FIFA)","competition":"WORLD (FIFA) - INTER CONFED. P.OFFS (CONCACAF v AFC)","home_team":"ΜΕΞΙΚΟ","away_team":"ΚΟΣΤΑ ΡΙΚΑ","home_rank":1.42,"draw_rank":3.5,"away_rank":5.9,"first_half":"2 - 0","result_score":"2 - 0","result":"1","home_team_goals":2,"away_team_goals":0,"total_goals":2},{"hash":"039ca4eeb6b45a371eec9fec26d99151","country":"MEXICO","competition":"MEXICO - CL2-P.OFF FINAL","home_team":"ΚΟΡΕΚΑΜΙΝΟΣ","away_team":"ΣΙΜΑΡΟΝΕΣ ΝΤΕ ΣΟΝΟΡΑ","home_rank":2.3,"draw_rank":3,"away_rank":2.6,"first_half":"1 - 0","result_score":"1 - 1","result":"X","home_team_goals":1,"away_team_goals":1,"total_goals":2},{"hash":"a90e0e58a869c318d923f88baeadd7d4","country":"MEXICO","competition":"MEXICO - CL2-P.OFF FINAL","home_team":"ΒΕΝΑΝΤΟΣ","away_team":"ΠΟΤΡΟΣ","home_rank":2.2,"draw_rank":2.95,"away_rank":2.8,"first_half":"1 - 0","result_score":"1 - 0","result":"1","home_team_goals":1,"away_team_goals":0,"total_goals":1},{"hash":"c5139a2a201850312d9772cbc5bb040b","country":"MEXICO","competition":"MEXICO - CL2-P.OFF FINAL","home_team":"ΚΑΦΕΤΑΛΕΡΟΣ ΝΤΕ ΤΑΠΑΤΣΟΥΛΑ","away_team":"ΜΟΥΡΘΙΕΛΑΓΚΟΣ","home_rank":1.98,"draw_rank":3.1,"away_rank":3.1,"first_half":"1 - 0","result_score":"2 - 1","result":"1","home_team_goals":2,"away_team_goals":1,"total_goals":3},{"hash":"e5e9544853175e2aafb74727f7ab6eee","country":"WORLD (FIFA)","competition":"WORLD (FIFA) - INTER CONFED. P.OFFS (CONCACAF v AFC)","home_team":"ΗΠΑ","away_team":"ΟΝΔΟΥΡΑ","home_rank":1.48,"draw_rank":3.6,"away_rank":5.2,"first_half":"3 - 0","result_score":"6 - 0","result":"1","home_team_goals":6,"away_team_goals":0,"total_goals":6},{"hash":"e8c1eff041c04cc629a732e751f91d04","country":"AUSTRALIA","competition":"AUSTRALIA - NSW P.OFF SF","home_team":"ΝΙΟΥΚΑΣΤΛ ΤΖΕΤΣ","away_team":"ΜΑΪΤΛΑΝΤ","home_rank":2.9,"draw_rank":3.9,"away_rank":1.82,"first_half":"","result_score":"","result":"","home_team_goals":null,"away_team_goals":null,"total_goals":null},{"hash":"1d7f5f4e43dac2593adfbdbfe687a0f5","country":"AUSTRALIA","competition":"AUSTRALIA - NSW P.OFF SF","home_team":"ΓΚΕΛΟΝΓΚ ΓΟΥΟΡΙΟΡΣ","away_team":"ΑΒΟΝΤΕΪΛ ΧΑΪΤΣ","home_rank":3.25,"draw_rank":3.45,"away_rank":1.82,"first_half":"0 - 0","result_score":"1 - 2","result":"2","home_team_goals":1,"away_team_goals":2,"total_goals":3},{"hash":"fee169d7c314983540f9f705361111a7","country":"AUSTRALIA","competition":"AUSTRALIA - NSW P.OFF SF","home_team":"ΧΑΚΟΑ","away_team":"ΣΙΔΝΕΪ ΓΙΟΥΝ.","home_rank":3.9,"draw_rank":3.9,"away_rank":1.57,"first_half":"2 - 1","result_score":"3 - 2","result":"1","home_team_goals":3,"away_team_goals":2,"total_goals":5},{"hash":"ac8a8c0b77b3e0ae0de666c6f91b5226","country":"JAPAN","competition":"JAPAN - J2 PROMOTION P.OFF FINAL","home_team":"ΜΙΤΟ","away_team":"ΕΧΙΜΕ","home_rank":2.2,"draw_rank":2.8,"away_rank":2.95,"first_half":"1 - 0","result_score":"1 - 0","result":"1","home_team_goals":1,"away_team_goals":0,"total_goals":1},{"hash":"dbf94522a5c1c16ec2a51a7b6590110d","country":"AUSTRALIA","competition":"AUSTRALIA - NSW P.OFF SF","home_team":"ΡΕΝΤΛΑΝΤ","away_team":"ΝΟΡΘΕΡΝ ΦΙΟΥΡΙ","home_rank":1.52,"draw_rank":4.1,"away_rank":4.1,"first_half":"0 - 2","result_score":"3 - 4","result":"2","home_team_goals":3,"away_team_goals":4,"total_goals":7}]